AUTHORS.rst
CONTRIBUTING.rst
HISTORY.rst
LICENSE
MANIFEST.in
README.rst
setup.cfg
setup.py
docs/Makefile
docs/authors.rst
docs/conf.py
docs/contributing.rst
docs/history.rst
docs/index.rst
docs/installation.rst
docs/make.bat
docs/readme.rst
docs/usage.rst
randgen_maptools/__init__.py
randgen_maptools/cli.py
randgen_maptools/randgen_maptools.py
randgen_maptools.egg-info/PKG-INFO
randgen_maptools.egg-info/SOURCES.txt
randgen_maptools.egg-info/dependency_links.txt
randgen_maptools.egg-info/entry_points.txt
randgen_maptools.egg-info/not-zip-safe
randgen_maptools.egg-info/requires.txt
randgen_maptools.egg-info/top_level.txt
tests/__init__.py
tests/test_randgen_maptools.py