Metadata-Version: 1.1
Name: randgen-maptools
Version: 0.1.1
Summary: Core map tools for randgen.io map generators.
Home-page: https://github.com/lxndrdagreat/randgen_maptools
Author: Dan Alexander
Author-email: lxndrdagreat@gmail.com
License: MIT license
Keywords: randgen_maptools
Platform: UNKNOWN
Classifier: Development Status :: 2 - Pre-Alpha
Classifier: Intended Audience :: Developers
Classifier: License :: OSI Approved :: MIT License
Classifier: Natural Language :: English
Classifier: Programming Language :: Python :: 2
Classifier: Programming Language :: Python :: 2.6
Classifier: Programming Language :: Python :: 2.7
Classifier: Programming Language :: Python :: 3
Classifier: Programming Language :: Python :: 3.3
Classifier: Programming Language :: Python :: 3.4
Classifier: Programming Language :: Python :: 3.5
